rosa/__init__.py
rosa/led.py
rosa/remote_cam.py
rosa/remote_io.py
rosa/rosa.py
rosa/version.py
rosa/wheel.py
rosa/vision/__init__.py
rosa/vision/line_tracking.py
rosa/vision/object_detector.py
rosa/vision/yolo_model.py
rosa/vision/yolov3/__init__.py
rosa/vision/yolov3/yolo.py
rosa/vision/yolov3/yolo3/__init__.py
rosa/vision/yolov3/yolo3/model.py
rosa/vision/yolov3/yolo3/utils.py
rosa_robot-0.1.0.dist-info/METADATA
rosa_robot-0.1.0.dist-info/WHEEL
rosa_robot-0.1.0.dist-info/top_level.txt
rosa_robot-0.1.0.dist-info/RECORD
