Metadata-Version: 2.1
Name: rosa-robot
Version: 0.1.0
Summary: Rosa robot Python API
Home-page: https://github.com/pollen-robotics/rosa
Author: Pollen Robotics
Author-email: UNKNOWN
License: UNKNOWN
Platform: UNKNOWN
Requires-Dist: Pillow
Requires-Dist: keras
Requires-Dist: matplotlib
Requires-Dist: numpy
Requires-Dist: opencv-python (<4,>3)
Requires-Dist: tensorflow
Requires-Dist: websocket-client
